<?xml version="1.0" encoding="UTF-8"?>
<objects serializationModel="Studio.02.02.00">
	<object class="EffectPreset" id="{bb61f99b-12f3-4c23-abbd-9b6deea7c7c4}">
		<property name="name">
			<value>Effect Chain</value>
		</property>
		<relationship name="folder">
			<destination>{46d6bde2-1d7e-4cb1-8299-d8eed50e2021}</destination>
		</relationship>
		<relationship name="effect">
			<destination>{d6fc9b92-1e54-48c0-9be2-10a6ffcd0a5a}</destination>
		</relationship>
	</object>
	<object class="EffectChain" id="{d6fc9b92-1e54-48c0-9be2-10a6ffcd0a5a}" />
</objects>
